laravel_queue/__init__.py
laravel_queue/exceptions.py
laravel_queue/job.py
laravel_python_sqs_queue-0.2.0.dist-info/LICENSE
laravel_python_sqs_queue-0.2.0.dist-info/METADATA
laravel_python_sqs_queue-0.2.0.dist-info/WHEEL
laravel_python_sqs_queue-0.2.0.dist-info/top_level.txt
laravel_python_sqs_queue-0.2.0.dist-info/RECORD
